tariff/__init__.py
tariff/__main__.py
tariff-1.0.0.dist-info/licenses/LICENSE
tariff-1.0.0.dist-info/METADATA
tariff-1.0.0.dist-info/WHEEL
tariff-1.0.0.dist-info/top_level.txt
tariff-1.0.0.dist-info/RECORD
