Metadata-Version: 2.4
Name: tariff
Version: 1.0.0
Summary: Make importing great again! A parody package that imposes tariffs on Python imports.
Home-page: https://github.com/hxu296/tariff
Author: Python Economist
Author-email: huan.xu71@gmail.com
Keywords: import,tariff,parody,monkey-patch
Classifier: Programming Language :: Python :: 3
Classifier: License :: OSI Approved :: MIT License
Classifier: Operating System :: OS Independent
Classifier: Development Status :: 3 - Alpha
Classifier: Intended Audience :: Developers
Classifier: Topic :: Software Development :: Libraries :: Python Modules
Classifier: Topic :: Utilities
Requires-Python: >=3.6
License-File: LICENSE
Dynamic: author
Dynamic: author-email
Dynamic: classifier
Dynamic: description
Dynamic: description-content-type
Dynamic: home-page
Dynamic: keywords
Dynamic: license-file
Dynamic: requires-python
Dynamic: summary
